{"date":"2026-04-18","collected":"2026-05-18T08:49:01.234Z","source":"open-meteo-archive","count":51,"stations":[{"id":"om_0","n":"Bologna","lat":44.494,"lon":11.343,"q":54,"p":"BO","mm":0},{"id":"om_1","n":"Ferrara","lat":44.836,"lon":11.62,"q":9,"p":"FE","mm":0},{"id":"om_2","n":"Modena","lat":44.646,"lon":10.926,"q":34,"p":"MO","mm":0},{"id":"om_3","n":"Reggio Emilia","lat":44.698,"lon":10.631,"q":58,"p":"RE","mm":0},{"id":"om_4","n":"Parma","lat":44.801,"lon":10.328,"q":57,"p":"PR","mm":0},{"id":"om_5","n":"Piacenza","lat":45.052,"lon":9.693,"q":61,"p":"PC","mm":0},{"id":"om_6","n":"Ravenna","lat":44.418,"lon":12.204,"q":4,"p":"RA","mm":0},{"id":"om_7","n":"Rimini","lat":44.059,"lon":12.565,"q":8,"p":"RN","mm":0},{"id":"om_8","n":"Forlì","lat":44.222,"lon":12.041,"q":33,"p":"FC","mm":0},{"id":"om_9","n":"Cesena","lat":44.133,"lon":12.243,"q":44,"p":"FC","mm":0},{"id":"om_10","n":"Imola","lat":44.352,"lon":11.714,"q":47,"p":"BO","mm":0},{"id":"om_11","n":"Faenza","lat":44.286,"lon":11.883,"q":35,"p":"RA","mm":0},{"id":"om_12","n":"Lugo","lat":44.42,"lon":11.904,"q":14,"p":"RA","mm":0},{"id":"om_13","n":"Comacchio","lat":44.695,"lon":12.183,"q":2,"p":"FE","mm":0},{"id":"om_14","n":"Fidenza","lat":44.865,"lon":10.063,"q":75,"p":"PR","mm":0},{"id":"om_15","n":"Guastalla","lat":44.921,"lon":10.66,"q":24,"p":"RE","mm":0},{"id":"om_16","n":"Carpi","lat":44.782,"lon":10.886,"q":26,"p":"MO","mm":0},{"id":"om_17","n":"Sassuolo","lat":44.547,"lon":10.785,"q":121,"p":"MO","mm":0},{"id":"om_18","n":"Pavullo","lat":44.337,"lon":10.834,"q":682,"p":"MO","mm":0},{"id":"om_19","n":"Lago Scaffaiolo","lat":44.175,"lon":10.714,"q":1773,"p":"MO","mm":0},{"id":"om_20","n":"Porretta Terme","lat":44.157,"lon":11.026,"q":348,"p":"BO","mm":0},{"id":"om_21","n":"Castel S.Pietro","lat":44.401,"lon":11.583,"q":75,"p":"BO","mm":0},{"id":"om_22","n":"Argenta","lat":44.614,"lon":11.833,"q":2,"p":"FE","mm":0},{"id":"om_23","n":"Boretto","lat":44.898,"lon":10.554,"q":25,"p":"RE","mm":0},{"id":"om_24","n":"Castelnovo Monti","lat":44.432,"lon":10.41,"q":724,"p":"RE","mm":0},{"id":"om_25","n":"Fiumalbo","lat":44.166,"lon":10.637,"q":953,"p":"MO","mm":0},{"id":"om_26","n":"Riccione","lat":44.003,"lon":12.655,"q":4,"p":"RN","mm":0},{"id":"om_27","n":"Cattolica","lat":43.966,"lon":12.73,"q":4,"p":"RN","mm":0},{"id":"om_28","n":"Sasso Marconi","lat":44.399,"lon":11.253,"q":124,"p":"BO","mm":0},{"id":"om_29","n":"Vergato","lat":44.281,"lon":11.108,"q":280,"p":"BO","mm":0},{"id":"om_30","n":"Piacenza Po","lat":45.06,"lon":9.72,"q":58,"p":"PC","mm":0},{"id":"om_31","n":"Ponte dell'Olio","lat":44.87,"lon":9.65,"q":215,"p":"PC","mm":0},{"id":"om_32","n":"Bedonia","lat":44.51,"lon":9.626,"q":450,"p":"PR","mm":0.2},{"id":"om_33","n":"Bore","lat":44.757,"lon":9.87,"q":630,"p":"PR","mm":0.1},{"id":"om_34","n":"Bardi","lat":44.633,"lon":9.722,"q":790,"p":"PR","mm":0.1},{"id":"om_35","n":"Langhirano","lat":44.62,"lon":10.266,"q":265,"p":"PR","mm":0},{"id":"om_36","n":"Sorbolo","lat":44.85,"lon":10.45,"q":28,"p":"PR","mm":0},{"id":"om_37","n":"Bismantova","lat":44.427,"lon":10.417,"q":1041,"p":"RE","mm":0.1},{"id":"om_38","n":"Busana","lat":44.367,"lon":10.317,"q":614,"p":"RE","mm":0.1},{"id":"om_39","n":"Fanano","lat":44.183,"lon":10.817,"q":650,"p":"MO","mm":0.1},{"id":"om_40","n":"Lama Mocogno","lat":44.267,"lon":10.733,"q":812,"p":"MO","mm":0},{"id":"om_41","n":"Reno Centese","lat":44.733,"lon":11.317,"q":8,"p":"FE","mm":0},{"id":"om_42","n":"Medicina","lat":44.483,"lon":11.633,"q":17,"p":"BO","mm":0},{"id":"om_43","n":"Molinella","lat":44.617,"lon":11.667,"q":7,"p":"BO","mm":0},{"id":"om_44","n":"Conselice","lat":44.517,"lon":11.833,"q":4,"p":"RA","mm":0},{"id":"om_45","n":"Cervia","lat":44.267,"lon":12.35,"q":2,"p":"RA","mm":0},{"id":"om_46","n":"Cesenatico","lat":44.2,"lon":12.383,"q":2,"p":"FC","mm":0},{"id":"om_47","n":"Savignano","lat":44.117,"lon":12.383,"q":10,"p":"FC","mm":0},{"id":"om_48","n":"Verghereto","lat":43.783,"lon":12,"q":1023,"p":"FC","mm":0},{"id":"om_49","n":"Bagno di Romagna","lat":43.833,"lon":11.95,"q":491,"p":"FC","mm":0},{"id":"om_0","n":"Santarcangelo","lat":44.067,"lon":12.45,"q":35,"p":"RN","mm":0}]}